Workbook
Name NativeTimeline_Dates: #N/A

Sheet Raw_Prices
A7: Dates | B7: Asset | C7: Price | D7: Year | E7: Month | F7: Check | H7: Average of Price | I7: Asset
A8: 45657 | B8: Debt_Fund | C8: 40.6174 | D8: =YEAR(A8) -> 2024 | E8: =TEXT(A8,"mmm") -> Dec | F8: =IF(C8<=0,"Error","Ok") -> Ok | H8: Year | I8: Debt_Fund | J8: GoldBeES | K8: HDFCBANK | L8: ITC | M8: NIFTY50 | N8: TCS
A9: 45657 | B9: GoldBeES | C9: 64 | D9: =YEAR(A9) -> 2024 | E9: =TEXT(A9,"mmm") -> Dec | F9: =IF(C9<=0,"Error","Ok") -> Ok | H9: 2020 | I9: 30.615833 | J9: 42.083333 | K9: 535.66667 | L9: 152.66667 | M9: 11150.5 | N9: 2010.5
A10: 45657 | B10: HDFCBANK | C10: 875 | D10: =YEAR(A10) -> 2024 | E10: =TEXT(A10,"mmm") -> Dec | F10: =IF(C10<=0,"Error","Ok") -> Ok | H10: 2021 | I10: 32.567358 | J10: 41.166667 | K10: 712.08333 | L10: 180.91667 | M10: 15942.75 | N10: 3005
A11: 45657 | B11: ITC | C11: 468 | D11: =YEAR(A11) -> 2024 | E11: =TEXT(A11,"mmm") -> Dec | F11: =IF(C11<=0,"Error","Ok") -> Ok | H11: 2022 | I11: 33.549467 | J11: 44 | K11: 701.58333 | L11: 257.91667 | M11: 17329.417 | N11: 3074.0833
A12: 45657 | B12: NIFTY50 | C12: 23645 | D12: =YEAR(A12) -> 2024 | E12: =TEXT(A12,"mmm") -> Dec | F12: =IF(C12<=0,"Error","Ok") -> Ok | H12: 2023 | I12: 35.94765 | J12: 50.583333 | K12: 779.41667 | L12: 394.66667 | M12: 18975.333 | N12: 3182.9167
A13: 45657 | B13: TCS | C13: 3957 | D13: =YEAR(A13) -> 2024 | E13: =TEXT(A13,"mmm") -> Dec | F13: =IF(C13<=0,"Error","Ok") -> Ok | H13: 2024 | I13: 39.075108 | J13: 60.416667 | K13: 791 | L13: 440.75 | M13: 23596.833 | N13: 3897.5
A14: 45626 | B14: Debt_Fund | C14: 40.4252 | D14: =YEAR(A14) -> 2024 | E14: =TEXT(A14,"mmm") -> Nov | F14: =IF(C14<=0,"Error","Ok") -> Ok | H14: Grand Total | I14: 34.351083 | J14: 47.65 | K14: 703.95 | L14: 285.38333 | M14: 17398.967 | N14: 3034
A15: 45626 | B15: GoldBeES | C15: 64 | D15: =YEAR(A15) -> 2024 | E15: =TEXT(A15,"mmm") -> Nov | F15: =IF(C15<=0,"Error","Ok") -> Ok
A16: 45626 | B16: HDFCBANK | C16: 886 | D16: =YEAR(A16) -> 2024 | E16: =TEXT(A16,"mmm") -> Nov | F16: =IF(C16<=0,"Error","Ok") -> Ok
A17: 45626 | B17: ITC | C17: 461 | D17: =YEAR(A17) -> 2024 | E17: =TEXT(A17,"mmm") -> Nov | F17: =IF(C17<=0,"Error","Ok") -> Ok
A18: 45626 | B18: NIFTY50 | C18: 24131 | D18: =YEAR(A18) -> 2024 | E18: =TEXT(A18,"mmm") -> Nov | F18: =IF(C18<=0,"Error","Ok") -> Ok
A19: 45626 | B19: TCS | C19: 4127 | D19: =YEAR(A19) -> 2024 | E19: =TEXT(A19,"mmm") -> Nov | F19: =IF(C19<=0,"Error","Ok") -> Ok
A20: 45596 | B20: Debt_Fund | C20: 40.1144 | D20: =YEAR(A20) -> 2024 | E20: =TEXT(A20,"mmm") -> Oct | F20: =IF(C20<=0,"Error","Ok") -> Ok
A21: 45596 | B21: GoldBeES | C21: 67 | D21: =YEAR(A21) -> 2024 | E21: =TEXT(A21,"mmm") -> Oct | F21: =IF(C21<=0,"Error","Ok") -> Ok
A22: 45596 | B22: HDFCBANK | C22: 856 | D22: =YEAR(A22) -> 2024 | E22: =TEXT(A22,"mmm") -> Oct | F22: =IF(C22<=0,"Error","Ok") -> Ok
A23: 45596 | B23: ITC | C23: 472 | D23: =YEAR(A23) -> 2024 | E23: =TEXT(A23,"mmm") -> Oct | F23: =IF(C23<=0,"Error","Ok") -> Ok
A24: 45596 | B24: NIFTY50 | C24: 24205 | D24: =YEAR(A24) -> 2024 | E24: =TEXT(A24,"mmm") -> Oct | F24: =IF(C24<=0,"Error","Ok") -> Ok
A25: 45596 | B25: TCS | C25: 3826 | D25: =YEAR(A25) -> 2024 | E25: =TEXT(A25,"mmm") -> Oct | F25: =IF(C25<=0,"Error","Ok") -> Ok
A26: 45565 | B26: Debt_Fund | C26: 39.9962 | D26: =YEAR(A26) -> 2024 | E26: =TEXT(A26,"mmm") -> Sep | F26: =IF(C26<=0,"Error","Ok") -> Ok
... A367: 43861 | B367: TCS | C367: 1822 | D367: =YEAR(A367) -> 2020 | E367: =TEXT(A367,"mmm") -> Jan | F367: =IF(C367<=0,"Error","Ok") -> Ok

Sheet Monthly_Returns
A7: Dates | B7: Asset | C7: Price | D7: Monthly_Return
A8: 43861 | B8: Debt_Fund | C8: 28.8169 | D8: =IF(B8=B7,(C8/C7)-1,"")
A9: 43890 | B9: Debt_Fund | C9: 29.3118 | D9: =IF(B9=B8,(C9/C8)-1,"") -> 0.01717395
A10: 43921 | B10: Debt_Fund | C10: 29.5003 | D10: =IF(B10=B9,(C10/C9)-1,"") -> 0.0064308572
A11: 43951 | B11: Debt_Fund | C11: 29.5014 | D11: =IF(B11=B10,(C11/C10)-1,"") -> 3.7287756e-05
A12: 43982 | B12: Debt_Fund | C12: 30.2358 | D12: =IF(B12=B11,(C12/C11)-1,"") -> 0.024893734
A13: 44012 | B13: Debt_Fund | C13: 30.695 | D13: =IF(B13=B12,(C13/C12)-1,"") -> 0.015187295
A14: 44043 | B14: Debt_Fund | C14: 31.2148 | D14: =IF(B14=B13,(C14/C13)-1,"") -> 0.016934354
A15: 44074 | B15: Debt_Fund | C15: 31.0405 | D15: =IF(B15=B14,(C15/C14)-1,"") -> -0.0055838897
A16: 44104 | B16: Debt_Fund | C16: 31.2111 | D16: =IF(B16=B15,(C16/C15)-1,"") -> 0.0054960455
A17: 44135 | B17: Debt_Fund | C17: 31.7827 | D17: =IF(B17=B16,(C17/C16)-1,"") -> 0.018313997
A18: 44165 | B18: Debt_Fund | C18: 31.992 | D18: =IF(B18=B17,(C18/C17)-1,"") -> 0.0065853436
A19: 44196 | B19: Debt_Fund | C19: 32.0877 | D19: =IF(B19=B18,(C19/C18)-1,"") -> 0.0029913728
... A367: 45657 | B367: TCS | C367: 3957 | D367: =IF(B367=B366,(C367/C366)-1,"") -> -0.041192149

Sheet Asset_Risk_Return
B5: ASSETS | C5: Avg Monthly Return | D5: Risk (Std Dev) | E5: Risk Category
B6: Debt_Fund | C6: =AVERAGEIF(Monthly_Returns!B8:B367,Asset_Risk_Return!B6,Monthly_Returns!D8:D367) -> 0.0058568962 | D6: {=_xlfn.STDEV.S(IF(Monthly_Returns!B8:B367=Asset_Risk_Return!B6,Monthly_Returns!D8:D367))} -> 0.0067702959 | E6: =IF(D6<0.01,"Very Low",IF(D6<0.04,"Low",IF(D6<0.07,"Medium","High"))) -> Very Low
B7: GoldBeES | C7: =AVERAGEIF(Monthly_Returns!B9:B367,Asset_Risk_Return!B7,Monthly_Returns!D9:D367) -> 0.010646009 | D7: {=_xlfn.STDEV.S(IF(Monthly_Returns!B9:B367=Asset_Risk_Return!B7,Monthly_Returns!D9:D367))} -> 0.041972858 | E7: =IF(D7<0.01,"Very Low",IF(D7<0.04,"Low",IF(D7<0.07,"Medium","High"))) -> Medium
B8: HDFCBANK | C8: =AVERAGEIF(Monthly_Returns!B10:B367,Asset_Risk_Return!B8,Monthly_Returns!D10:D367) -> 0.0096417272 | D8: {=_xlfn.STDEV.S(IF(Monthly_Returns!B10:B367=Asset_Risk_Return!B8,Monthly_Returns!D10:D367))} -> 0.072919617 | E8: =IF(D8<0.01,"Very Low",IF(D8<0.04,"Low",IF(D8<0.07,"Medium","High"))) -> High
B9: ITC | C9: =AVERAGEIF(Monthly_Returns!B11:B367,Asset_Risk_Return!B9,Monthly_Returns!D11:D367) -> 0.018334468 | D9: {=_xlfn.STDEV.S(IF(Monthly_Returns!B11:B367=Asset_Risk_Return!B9,Monthly_Returns!D11:D367))} -> 0.068904344 | E9: =IF(D9<0.01,"Very Low",IF(D9<0.04,"Low",IF(D9<0.07,"Medium","High"))) -> Medium
B10: NIFTY50 | C10: =AVERAGEIF(Monthly_Returns!B12:B367,Asset_Risk_Return!B10,Monthly_Returns!D12:D367) -> 0.013142797 | D10: {=_xlfn.STDEV.S(IF(Monthly_Returns!B12:B367=Asset_Risk_Return!B10,Monthly_Returns!D12:D367))} -> 0.054593619 | E10: =IF(D10<0.01,"Very Low",IF(D10<0.04,"Low",IF(D10<0.07,"Medium","High"))) -> Medium
B11: TCS | C11: =AVERAGEIF(Monthly_Returns!B13:B367,Asset_Risk_Return!B11,Monthly_Returns!D13:D367) -> 0.015065964 | D11: {=_xlfn.STDEV.S(IF(Monthly_Returns!B13:B367=Asset_Risk_Return!B11,Monthly_Returns!D13:D367))} -> 0.061886072 | E11: =IF(D11<0.01,"Very Low",IF(D11<0.04,"Low",IF(D11<0.07,"Medium","High"))) -> Medium

Sheet Returns_Matrix
A4: Average of Monthly_Return | B4: Asset
A5: Dates | B5: Debt_Fund | C5: GoldBeES | D5: HDFCBANK | E5: ITC | F5: NIFTY50 | G5: TCS
A6: 43890 | B6: 0.01717395 | C6: 0.027777778 | D6: -0.039586919 | E6: -0.15846995 | F6: -0.063534526 | G6: -0.035675082
A7: 43921 | B7: 0.0064308572 | C7: 0.027027027 | D7: -0.2688172 | E7: -0.12987013 | F7: -0.23245849 | G7: -0.08708025
A8: 43951 | B8: 3.7287756e-05 | C8: 0.13157895 | D8: 0.16176471 | E8: 0.059701493 | F8: 0.14677832 | G8: 0.11159601
A9: 43982 | B9: 0.024893734 | C9: -0.046511628 | D9: -0.048523207 | E9: 0.084507042 | F9: -0.028397566 | G9: -0.021312395
A10: 44012 | B10: 0.015187295 | C10: 0.048780488 | D10: 0.11973392 | E10: -0.012987013 | F10: 0.075365344 | G10: 0.056160458
A11: 44043 | B11: 0.016934354 | C11: 0.093023256 | D11: -0.031683168 | E11: -0.0065789474 | F11: 0.074839837 | G11: 0.098752035
A12: 44074 | B12: -0.0055838897 | C12: -0.042553191 | D12: 0.079754601 | E12: 0.033112583 | F12: 0.028447575 | G12: -0.0083950617
A13: 44104 | B13: 0.0054960455 | C13: -0.022222222 | D13: -0.03219697 | E13: -0.096153846 | F13: -0.012293642 | G13: 0.10408367
A14: 44135 | B14: 0.018313997 | C14: 0 | D14: 0.097847358 | E14: -0.042553191 | F14: 0.03502845 | G14: 0.069463239
A15: 44165 | B15: 0.0065853436 | C15: -0.022727273 | D15: 0.21568627 | E15: 0.17777778 | F15: 0.11398385 | G15: 0.0097005483
A16: 44196 | B16: 0.0029913728 | C16: 0.023255814 | D16: -0.0029325513 | E16: 0.075471698 | F16: 0.078109338 | G16: 0.068086884
A17: 44227 | B17: -0.0012341177 | C17: -0.022727273 | D17: -0.030882353 | E17: -0.029239766 | F17: -0.024817623 | G17: 0.087211576
... A64: 45657 | B64: 0.0047544601 | C64: 0 | D64: -0.01241535 | E64: 0.015184382 | F64: -0.020140069 | G64: -0.041192149

Sheet Correlation
A6: ASSET *ASSET | B6: Debt_Fund | C6: GoldBeES | D6: HDFCBANK | E6: ITC | F6: NIFTY50 | G6: TCS
A7: Debt_Fund | B7: =CORREL(Returns_Matrix!B6:B64,Returns_Matrix!$B$6:$B$64) -> 1 | C7: =CORREL(Returns_Matrix!C6:C64,Returns_Matrix!$B$6:$B$64) -> 0.12981595 | D7: =CORREL(Returns_Matrix!D6:D64,Returns_Matrix!$B$6:$B$64) -> -0.040326141 | E7: =CORREL(Returns_Matrix!E6:E64,Returns_Matrix!$B$6:$B$64) -> 0.0039633333 | F7: =CORREL(Returns_Matrix!F6:F64,Returns_Matrix!$B$6:$B$64) -> 0.054120731 | G7: =CORREL(Returns_Matrix!G6:G64,Returns_Matrix!$B$6:$B$64) -> 0.22320488
A8: GoldBeES | B8: =CORREL(Returns_Matrix!B6:B64,Returns_Matrix!$C$6:$C$64) -> 0.12981595 | C8: =CORREL(Returns_Matrix!C6:C64,Returns_Matrix!$C$6:$C$64) -> 1 | D8: =CORREL(Returns_Matrix!D6:D64,Returns_Matrix!$C$6:$C$64) -> 0.033491691 | E8: =CORREL(Returns_Matrix!E6:E64,Returns_Matrix!$C$6:$C$64) -> -0.16292893 | F8: =CORREL(Returns_Matrix!F6:F64,Returns_Matrix!$C$6:$C$64) -> 0.056352813 | G8: =CORREL(Returns_Matrix!G6:G64,Returns_Matrix!$C$6:$C$64) -> -0.16225037
A9: HDFCBANK | B9: =CORREL(Returns_Matrix!B6:B64,Returns_Matrix!$D$6:$D$64) -> -0.040326141 | C9: =CORREL(Returns_Matrix!C6:C64,Returns_Matrix!$D$6:$D$64) -> 0.033491691 | D9: =CORREL(Returns_Matrix!D6:D64,Returns_Matrix!$D$6:$D$64) -> 1 | E9: =CORREL(Returns_Matrix!E6:E64,Returns_Matrix!$D$6:$D$64) -> 0.40749196 | F9: =CORREL(Returns_Matrix!F6:F64,Returns_Matrix!$D$6:$D$64) -> 0.80158223 | G9: =CORREL(Returns_Matrix!G6:G64,Returns_Matrix!$D$6:$D$64) -> 0.30572275
A10: ITC | B10: =CORREL(Returns_Matrix!B6:B64,Returns_Matrix!$E$6:$E$64) -> 0.0039633333 | C10: =CORREL(Returns_Matrix!C6:C64,Returns_Matrix!$E$6:$E$64) -> -0.16292893 | D10: =CORREL(Returns_Matrix!D6:D64,Returns_Matrix!$E$6:$E$64) -> 0.40749196 | E10: =CORREL(Returns_Matrix!E6:E64,Returns_Matrix!$E$6:$E$64) -> 1 | F10: =CORREL(Returns_Matrix!F6:F64,Returns_Matrix!$E$6:$E$64) -> 0.5128896 | G10: =CORREL(Returns_Matrix!G6:G64,Returns_Matrix!$E$6:$E$64) -> 0.18361688
A11: NIFTY50 | B11: =CORREL(Returns_Matrix!B6:B64,Returns_Matrix!$F$6:$F$64) -> 0.054120731 | C11: =CORREL(Returns_Matrix!C6:C64,Returns_Matrix!$F$6:$F$64) -> 0.056352813 | D11: =CORREL(Returns_Matrix!D6:D64,Returns_Matrix!$F$6:$F$64) -> 0.80158223 | E11: =CORREL(Returns_Matrix!E6:E64,Returns_Matrix!$F$6:$F$64) -> 0.5128896 | F11: =CORREL(Returns_Matrix!F6:F64,Returns_Matrix!$F$6:$F$64) -> 1 | G11: =CORREL(Returns_Matrix!G6:G64,Returns_Matrix!$F$6:$F$64) -> 0.53402607
A12: TCS | B12: =CORREL(Returns_Matrix!B6:B64,Returns_Matrix!$G$6:$G$64) -> 0.22320488 | C12: =CORREL(Returns_Matrix!C6:C64,Returns_Matrix!$G$6:$G$64) -> -0.16225037 | D12: =CORREL(Returns_Matrix!D6:D64,Returns_Matrix!$G$6:$G$64) -> 0.30572275 | E12: =CORREL(Returns_Matrix!E6:E64,Returns_Matrix!$G$6:$G$64) -> 0.18361688 | F12: =CORREL(Returns_Matrix!F6:F64,Returns_Matrix!$G$6:$G$64) -> 0.53402607 | G12: =CORREL(Returns_Matrix!G6:G64,Returns_Matrix!$G$6:$G$64) -> 1
A14: COLOR | B14: MEANING
A15: Green | B15: Strong Positive
A16: White | B16: Neutral
A17: Red | B17: Negative

Sheet RISK ANALYSIS
R5: Criteria | S5: Numbers
A6: Average of Monthly_Return | B6: Asset | I6: Asset | J6: Monthly Volatility | K6: Annual Volatility | L6: Risk Category | R6: Low_Max | S6: =_xlfn.PERCENTILE.INC(J7:J12,0.33) -> 0.050176353
A7: Dates | B7: Debt_Fund | C7: GoldBeES | D7: HDFCBANK | E7: ITC | F7: NIFTY50 | G7: TCS | I7: Debt_Fund | J7: =_xlfn.STDEV.S(B8:B66) -> 0.0067702959 | K7: =J7*SQRT(12) -> 0.023452993 | L7: =IF($J7<=$S$6,"Low Risk",IF($J7<=$S$7,"Medium Risk","High Risk")) -> Low Risk | R7: Medium_Max | S7: =_xlfn.PERCENTILE.INC(J7:J12,0.66) -> 0.063991554
A8: 43890 | B8: 0.01717395 | C8: 0.027777778 | D8: -0.039586919 | E8: -0.15846995 | F8: -0.063534526 | G8: -0.035675082 | I8: GoldBeES | J8: =_xlfn.STDEV.S(C8:C66) -> 0.041972858 | K8: =J8*SQRT(12) -> 0.14539825 | L8: =IF($J8<=$S$6,"Low Risk",IF($J8<=$S$7,"Medium Risk","High Risk")) -> Low Risk
A9: 43921 | B9: 0.0064308572 | C9: 0.027027027 | D9: -0.2688172 | E9: -0.12987013 | F9: -0.23245849 | G9: -0.08708025 | I9: HDFCBANK | J9: =_xlfn.STDEV.S(D8:D66) -> 0.072919617 | K9: =J9*SQRT(12) -> 0.25260096 | L9: =IF($J9<=$S$6,"Low Risk",IF($J9<=$S$7,"Medium Risk","High Risk")) -> High Risk
A10: 43951 | B10: 3.7287756e-05 | C10: 0.13157895 | D10: 0.16176471 | E10: 0.059701493 | F10: 0.14677832 | G10: 0.11159601 | I10: ITC | J10: =_xlfn.STDEV.S(E8:E66) -> 0.068904344 | K10: =J10*SQRT(12) -> 0.23869165 | L10: =IF($J10<=$S$6,"Low Risk",IF($J10<=$S$7,"Medium Risk","High Risk")) -> High Risk
A11: 43982 | B11: 0.024893734 | C11: -0.046511628 | D11: -0.048523207 | E11: 0.084507042 | F11: -0.028397566 | G11: -0.021312395 | I11: NIFTY50 | J11: =_xlfn.STDEV.S(F8:F66) -> 0.054593619 | K11: =J11*SQRT(12) -> 0.18911784 | L11: =IF($J11<=$S$6,"Low Risk",IF($J11<=$S$7,"Medium Risk","High Risk")) -> Medium Risk
A12: 44012 | B12: 0.015187295 | C12: 0.048780488 | D12: 0.11973392 | E12: -0.012987013 | F12: 0.075365344 | G12: 0.056160458 | I12: TCS | J12: =_xlfn.STDEV.S(G8:G66) -> 0.061886072 | K12: =J12*SQRT(12) -> 0.21437964 | L12: =IF($J12<=$S$6,"Low Risk",IF($J12<=$S$7,"Medium Risk","High Risk")) -> Medium Risk
A13: 44043 | B13: 0.016934354 | C13: 0.093023256 | D13: -0.031683168 | E13: -0.0065789474 | F13: 0.074839837 | G13: 0.098752035
A14: 44074 | B14: -0.0055838897 | C14: -0.042553191 | D14: 0.079754601 | E14: 0.033112583 | F14: 0.028447575 | G14: -0.0083950617
A15: 44104 | B15: 0.0054960455 | C15: -0.022222222 | D15: -0.03219697 | E15: -0.096153846 | F15: -0.012293642 | G15: 0.10408367
A16: 44135 | B16: 0.018313997 | C16: 0 | D16: 0.097847358 | E16: -0.042553191 | F16: 0.03502845 | G16: 0.069463239
A17: 44165 | B17: 0.0065853436 | C17: -0.022727273 | D17: 0.21568627 | E17: 0.17777778 | F17: 0.11398385 | G17: 0.0097005483
A18: 44196 | B18: 0.0029913728 | C18: 0.023255814 | D18: -0.0029325513 | E18: 0.075471698 | F18: 0.078109338 | G18: 0.068086884
A19: 44227 | B19: -0.0012341177 | C19: -0.022727273 | D19: -0.030882353 | E19: -0.029239766 | F19: -0.024817623 | G19: 0.087211576
A20: 44255 | B20: -0.013888499 | C20: -0.069767442 | D20: 0.10318665 | E20: 0.0060240964 | F20: 0.065566557 | G20: -0.067985612
A21: 44286 | B21: 0.012590577 | C21: -0.05 | D21: -0.027510316 | E21: 0.095808383 | F21: 0.011150114 | G21: 0.097645697
A22: 44316 | B22: 0.0092653644 | C22: 0.078947368 | D22: -0.053748232 | E22: -0.071038251 | F22: -0.0040841331 | G22: -0.044655415
A23: 44347 | B23: 0.0044492746 | C23: 0.048780488 | D23: 0.073243647 | E23: 0.070588235 | F23: 0.065067323 | G23: 0.040853883
A24: 44377 | B24: 0.00070281217 | C24: -0.046511628 | D24: -0.012534819 | E24: -0.065934066 | F24: 0.0089199769 | G24: 0.064002829
... A66: 45657 | B66: 0.0047544601 | C66: 0 | D66: -0.01241535 | E66: 0.015184382 | F66: -0.020140069 | G66: -0.041192149

Sheet Portfolio_Analysis
A4: Asset | B4: Weight | C4: Weighted Volatility | G4: Metric | H4: Value
A5: Debt_Fund | B5: =IF('RISK ANALYSIS'!K7<=0.05,0.3 - ('RISK ANALYSIS'!K7/0.05)*0.1,IF('RISK ANALYSIS'!K7<=0.2,0.25 -(('RISK ANALYSIS'!K7-0.05)/0.15)*0.1,IF('RISK ANALYSIS'!K7<=0.3,0.15-(('RISK ANALYSIS'!K7 -0.2)/0.1)*0.1,0.05))) -> 0.25309401 | C5: =B15*B5 -> 0.017788144 | G5: Expected Annual Return | H5: =SUMPRODUCT(B5:B10,B15:B20) -> 0.12668001
A6: GoldBeES | B6: =IF('RISK ANALYSIS'!K8<=0.05,0.3 - ('RISK ANALYSIS'!K8/0.05)*0.1,IF('RISK ANALYSIS'!K8<=0.2,0.25 -(('RISK ANALYSIS'!K8-0.05)/0.15)*0.1,IF('RISK ANALYSIS'!K8<=0.3,0.15-(('RISK ANALYSIS'!K8 -0.2)/0.1)*0.1,0.05))) -> 0.18640117 | C6: =B16*B6 -> 0.023813142 | G6: Portfolio Risk Level | H6: =IF(SUM(C5:C10)<0.12,"Low",IF(SUM(C5:C10)<0.2,"Medium","High")) -> Medium
A7: HDFCBANK | B7: =IF('RISK ANALYSIS'!K9<=0.05,0.3 - ('RISK ANALYSIS'!K9/0.05)*0.1,IF('RISK ANALYSIS'!K9<=0.2,0.25 -(('RISK ANALYSIS'!K9-0.05)/0.15)*0.1,IF('RISK ANALYSIS'!K9<=0.3,0.15-(('RISK ANALYSIS'!K9 -0.2)/0.1)*0.1,0.05))) -> 0.097399038 | C7: =B17*B7 -> 0.011269139 | G7: Benchmark (NIFTY50) | H7: {=(PRODUCT(1+Returns_Matrix!F6:F64))^(12/COUNT(Returns_Matrix!F6:F64))-1} -> 0.14865677
A8: ITC | B8: =IF('RISK ANALYSIS'!K10<=0.05,0.3 - ('RISK ANALYSIS'!K10/0.05)*0.1,IF('RISK ANALYSIS'!K10<=0.2,0.25 -(('RISK ANALYSIS'!K10-0.05)/0.15)*0.1,IF('RISK ANALYSIS'!K10<=0.3,0.15-(('RISK ANALYSIS'!K10 -0.2)/0.1)*0.1,0.05))) -> 0.11130835 | C8: =B18*B8 -> 0.024489352 | G8: Outperformance Status | H8: =IF(H5-H7>0.1,"Outperformed",IF(H5-H7>0,"Slightly Outperformed",IF(H5-H7>-0.01,"Slightly Underperformed","Underperformed"))) -> Underperformed
A9: NIFTY50 | B9: =IF('RISK ANALYSIS'!K11<=0.05,0.3 - ('RISK ANALYSIS'!K11/0.05)*0.1,IF('RISK ANALYSIS'!K11<=0.2,0.25 -(('RISK ANALYSIS'!K11-0.05)/0.15)*0.1,IF('RISK ANALYSIS'!K11<=0.3,0.15-(('RISK ANALYSIS'!K11 -0.2)/0.1)*0.1,0.05))) -> 0.15725477 | C9: =B19*B9 -> 0.024801211
A10: TCS | B10: =IF('RISK ANALYSIS'!K12<=0.05,0.3 - ('RISK ANALYSIS'!K12/0.05)*0.1,IF('RISK ANALYSIS'!K12<=0.2,0.25 -(('RISK ANALYSIS'!K12-0.05)/0.15)*0.1,IF('RISK ANALYSIS'!K12<=0.3,0.15-(('RISK ANALYSIS'!K12 -0.2)/0.1)*0.1,0.05))) -> 0.13562036 | C10: =B20*B10 -> 0.024519017
A14: Asset | B14: Avg Annual Return | C14: Annual Volatility | D14: Risk Category | E14: Risk Score | G14: Asset_01 | H14: Asset_02 | I14: Correlation | J14: Interpretation
A15: Debt_Fund | B15: =AVERAGE(Returns_Matrix!B6:B64)*12 -> 0.070282754 | C15: ='RISK ANALYSIS'!J7*SQRT((12)) -> 0.023452993 | D15: =IF(C15<0.03,"Low",IF(C15<0.2,"Medium","High")) -> Low | E15: =IF(D15="Low",1,IF(D15="Medium",2,3)) -> 1 | G15: Debt_Fund | H15: NIFTY50 | I15: =CORREL(Returns_Matrix!B6:B64,Returns_Matrix!$F$6:$F$64) -> 0.054120731 | J15: =IF(I15<0.3,"Very Low (Diversifier)",IF(I15<0.7,"Moderate","Highly Correlated")) -> Very Low (Diversifier)
A16: GoldBeES | B16: =AVERAGE(Returns_Matrix!C6:C64)*12 -> 0.12775211 | C16: ='RISK ANALYSIS'!J8*SQRT((12)) -> 0.14539825 | D16: =IF(C16<0.03,"Low",IF(C16<0.2,"Medium","High")) -> Medium | E16: =IF(D16="Low",1,IF(D16="Medium",2,3)) -> 2 | G16: GoldBeES | H16: NIFTY50 | I16: =CORREL(Returns_Matrix!C6:C64,Returns_Matrix!$F$6:$F$64) -> 0.056352813 | J16: =IF(I16<0.3,"Very Low (Diversifier)",IF(I16<0.7,"Moderate","Highly Correlated")) -> Very Low (Diversifier)
A17: HDFCBANK | B17: =AVERAGE(Returns_Matrix!D6:D64)*12 -> 0.11570073 | C17: ='RISK ANALYSIS'!J9*SQRT((12)) -> 0.25260096 | D17: =IF(C17<0.03,"Low",IF(C17<0.2,"Medium","High")) -> High | E17: =IF(D17="Low",1,IF(D17="Medium",2,3)) -> 3 | G17: HDFCBANK | H17: NIFTY50 | I17: =CORREL(Returns_Matrix!D6:D64,Returns_Matrix!$F$6:$F$64) -> 0.80158223 | J17: =IF(I17<0.3,"Very Low (Diversifier)",IF(I17<0.7,"Moderate","Highly Correlated")) -> Highly Correlated
A18: ITC | B18: =AVERAGE(Returns_Matrix!E6:E64)*12 -> 0.22001361 | C18: ='RISK ANALYSIS'!J10*SQRT((12)) -> 0.23869165 | D18: =IF(C18<0.03,"Low",IF(C18<0.2,"Medium","High")) -> High | E18: =IF(D18="Low",1,IF(D18="Medium",2,3)) -> 3 | G18: ITC | H18: TCS | I18: =CORREL(Returns_Matrix!E6:E64,Returns_Matrix!$G$6:$G$64) -> 0.18361688 | J18: =IF(I18<0.3,"Very Low (Diversifier)",IF(I18<0.7,"Moderate","Highly Correlated")) -> Very Low (Diversifier)
A19: NIFTY50 | B19: =AVERAGE(Returns_Matrix!F6:F64)*12 -> 0.15771357 | C19: ='RISK ANALYSIS'!J11*SQRT((12)) -> 0.18911784 | D19: =IF(C19<0.03,"Low",IF(C19<0.2,"Medium","High")) -> Medium | E19: =IF(D19="Low",1,IF(D19="Medium",2,3)) -> 2
A20: TCS | B20: =AVERAGE(Returns_Matrix!G6:G64)*12 -> 0.18079157 | C20: ='RISK ANALYSIS'!J12*SQRT((12)) -> 0.21437964 | D20: =IF(C20<0.03,"Low",IF(C20<0.2,"Medium","High")) -> High | E20: =IF(D20="Low",1,IF(D20="Medium",2,3)) -> 3

Sheet Dashboard
C22: Column1 | D22: Debt_Fund | E22: GoldBeES | F22: HDFCBANK | G22: ITC | H22: NIFTY50 | I22: TCS
C23: Debt_Fund | D23: =CORREL(Returns_Matrix!B6:B64,Returns_Matrix!$B$6:$B$64) -> 1 | E23: =CORREL(Returns_Matrix!C6:C64,Returns_Matrix!$B$6:$B$64) -> 0.12981595 | F23: =CORREL(Returns_Matrix!D6:D64,Returns_Matrix!$B$6:$B$64) -> -0.040326141 | G23: =CORREL(Returns_Matrix!E6:E64,Returns_Matrix!$B$6:$B$64) -> 0.0039633333 | H23: =CORREL(Returns_Matrix!F6:F64,Returns_Matrix!$B$6:$B$64) -> 0.054120731 | I23: =CORREL(Returns_Matrix!G6:G64,Returns_Matrix!$B$6:$B$64) -> 0.22320488
C24: GoldBeES | D24: =CORREL(Returns_Matrix!B6:B64,Returns_Matrix!$C$6:$C$64) -> 0.12981595 | E24: =CORREL(Returns_Matrix!C6:C64,Returns_Matrix!$C$6:$C$64) -> 1 | F24: =CORREL(Returns_Matrix!D6:D64,Returns_Matrix!$C$6:$C$64) -> 0.033491691 | G24: =CORREL(Returns_Matrix!E6:E64,Returns_Matrix!$C$6:$C$64) -> -0.16292893 | H24: =CORREL(Returns_Matrix!F6:F64,Returns_Matrix!$C$6:$C$64) -> 0.056352813 | I24: =CORREL(Returns_Matrix!G6:G64,Returns_Matrix!$C$6:$C$64) -> -0.16225037
C25: HDFCBANK | D25: =CORREL(Returns_Matrix!B6:B64,Returns_Matrix!$D$6:$D$64) -> -0.040326141 | E25: =CORREL(Returns_Matrix!C6:C64,Returns_Matrix!$D$6:$D$64) -> 0.033491691 | F25: =CORREL(Returns_Matrix!D6:D64,Returns_Matrix!$D$6:$D$64) -> 1 | G25: =CORREL(Returns_Matrix!E6:E64,Returns_Matrix!$D$6:$D$64) -> 0.40749196 | H25: =CORREL(Returns_Matrix!F6:F64,Returns_Matrix!$D$6:$D$64) -> 0.80158223 | I25: =CORREL(Returns_Matrix!G6:G64,Returns_Matrix!$D$6:$D$64) -> 0.30572275
C26: ITC | D26: =CORREL(Returns_Matrix!B6:B64,Returns_Matrix!$E$6:$E$64) -> 0.0039633333 | E26: =CORREL(Returns_Matrix!C6:C64,Returns_Matrix!$E$6:$E$64) -> -0.16292893 | F26: =CORREL(Returns_Matrix!D6:D64,Returns_Matrix!$E$6:$E$64) -> 0.40749196 | G26: =CORREL(Returns_Matrix!E6:E64,Returns_Matrix!$E$6:$E$64) -> 1 | H26: =CORREL(Returns_Matrix!F6:F64,Returns_Matrix!$E$6:$E$64) -> 0.5128896 | I26: =CORREL(Returns_Matrix!G6:G64,Returns_Matrix!$E$6:$E$64) -> 0.18361688
C27: NIFTY50 | D27: =CORREL(Returns_Matrix!B6:B64,Returns_Matrix!$F$6:$F$64) -> 0.054120731 | E27: =CORREL(Returns_Matrix!C6:C64,Returns_Matrix!$F$6:$F$64) -> 0.056352813 | F27: =CORREL(Returns_Matrix!D6:D64,Returns_Matrix!$F$6:$F$64) -> 0.80158223 | G27: =CORREL(Returns_Matrix!E6:E64,Returns_Matrix!$F$6:$F$64) -> 0.5128896 | H27: =CORREL(Returns_Matrix!F6:F64,Returns_Matrix!$F$6:$F$64) -> 1 | I27: =CORREL(Returns_Matrix!G6:G64,Returns_Matrix!$F$6:$F$64) -> 0.53402607
C28: TCS | D28: =CORREL(Returns_Matrix!B6:B64,Returns_Matrix!$G$6:$G$64) -> 0.22320488 | E28: =CORREL(Returns_Matrix!C6:C64,Returns_Matrix!$G$6:$G$64) -> -0.16225037 | F28: =CORREL(Returns_Matrix!D6:D64,Returns_Matrix!$G$6:$G$64) -> 0.30572275 | G28: =CORREL(Returns_Matrix!E6:E64,Returns_Matrix!$G$6:$G$64) -> 0.18361688 | H28: =CORREL(Returns_Matrix!F6:F64,Returns_Matrix!$G$6:$G$64) -> 0.53402607 | I28: =CORREL(Returns_Matrix!G6:G64,Returns_Matrix!$G$6:$G$64) -> 1
